{
    "month": {
        "1": {
            "name": "বৈশাখ",
            "day": "31",
            "start": "6",
            "krishnaAkadoshi": [2, 31],
            "sukloAkadoshi": [17],
            "purnima": 21,
            "omabossa": 6
        },
        "2": {
            "name": "জৈষ্ঠ্য",
            "day": "31",
            "start": "2"
        },
        "3": {
            "name": "আষাঢ়",
            "day": "32",
            "start": "5"
        },
        "4": {
            "name": "শ্রাবণ",
            "day": "31",
            "start": "2"
        },
        "5": {
            "name": "ভ্রাদ্র",
            "day": "31",
            "start": "5"
        },
        "6": {
            "name": "আশ্বিন",
            "day": "31",
            "start": "1"
        },
        "7": {
            "name": "কার্তিক",
            "day": "30",
            "start": "4"
        },
        "8": {
            "name": "অগ্রহায়ণ",
            "day": "29",
            "start": "6"
        },
        "9": {
            "name": "পৌষ",
            "day": "30",
            "start": "0"
        },
        "10": {
            "name": "মাঘ",
            "day": "29",
            "start": "2"
        },
        "11": {
            "name": "ফাল্গুন",
            "day": "30",
            "start": "3"
        },
        "12": {
            "name": "চৈত্র",
            "day": "30",
            "start": "5"
        }
    }
}